HTMLTestRunner/__init__.py
HTMLTestRunner/runner.py
HTMLTestRunner/static/script.js
HTMLTestRunner/static/stylesheet.css
HTMLTestRunner/templates/template.html
htmltestrunner_rv-1.1.3.dist-info/licenses/LICENSE.txt
htmltestrunner_rv-1.1.3.dist-info/METADATA
htmltestrunner_rv-1.1.3.dist-info/WHEEL
htmltestrunner_rv-1.1.3.dist-info/top_level.txt
htmltestrunner_rv-1.1.3.dist-info/RECORD
