Metadata-Version: 2.4
Name: HTMLTestRunner-rv
Version: 1.1.3
Summary: HTMLTestRunner for unit test framework
Home-page: https://github.com/ravikiranb36/HTMLTestRunner.io.git
Author: Ravikirana B
Author-email: ravikiranb36@gmail.com
License: MIT
Keywords: HtmlTestRunner TestRunner Html Reports
Classifier: Programming Language :: Python :: 3
Classifier: License :: OSI Approved :: MIT License
Classifier: Operating System :: OS Independent
Requires-Python: >=3.6
License-File: LICENSE.txt
Requires-Dist: pyparsing>=2.4.7
Requires-Dist: jinja2>=2.11
Dynamic: author
Dynamic: author-email
Dynamic: classifier
Dynamic: description
Dynamic: description-content-type
Dynamic: home-page
Dynamic: keywords
Dynamic: license
Dynamic: license-file
Dynamic: requires-dist
Dynamic: requires-python
Dynamic: summary
